kgclitest/__init__.py
kgclitest/greetings.py
kgclitest-0.3.0.dist-info/METADATA
kgclitest-0.3.0.dist-info/WHEEL
kgclitest-0.3.0.dist-info/entry_points.txt
kgclitest-0.3.0.dist-info/RECORD
